aspose/cellsgridjs/py.typed
aspose/pycore/py.typed
aspose/pycore/__init__.pyi
aspose/pyreflection/py.typed
aspose/pyreflection/__init__.pyi
aspose/pydrawing/py.typed
aspose/pydrawing/__init__.pyi
aspose/pydrawing/design.pyi
aspose/pydrawing/drawing2d.pyi
aspose/pydrawing/imaging.pyi
aspose/pydrawing/printing.pyi
aspose/pydrawing/text.pyi
aspose/cellsgridjs/__init__.pyi
.__pyi_patched
aspose/__init__.py
aspose/cellsgridjs.cpython-310-x86_64-linux-gnu.so
aspose/cellsgridjs.cpython-311-x86_64-linux-gnu.so
aspose/cellsgridjs.cpython-312-x86_64-linux-gnu.so
aspose/cellsgridjs.cpython-313-x86_64-linux-gnu.so
aspose/cellsgridjs.cpython-38-x86_64-linux-gnu.so
aspose/cellsgridjs.cpython-39-x86_64-linux-gnu.so
aspose/pycore.cpython-310-x86_64-linux-gnu.so
aspose/pycore.cpython-311-x86_64-linux-gnu.so
aspose/pycore.cpython-312-x86_64-linux-gnu.so
aspose/pycore.cpython-313-x86_64-linux-gnu.so
aspose/pycore.cpython-38-x86_64-linux-gnu.so
aspose/pycore.cpython-39-x86_64-linux-gnu.so
aspose/pydrawing.cpython-310-x86_64-linux-gnu.so
aspose/pydrawing.cpython-311-x86_64-linux-gnu.so
aspose/pydrawing.cpython-312-x86_64-linux-gnu.so
aspose/pydrawing.cpython-313-x86_64-linux-gnu.so
aspose/pydrawing.cpython-38-x86_64-linux-gnu.so
aspose/pydrawing.cpython-39-x86_64-linux-gnu.so
aspose/pygc.cpython-310-x86_64-linux-gnu.so
aspose/pygc.cpython-311-x86_64-linux-gnu.so
aspose/pygc.cpython-312-x86_64-linux-gnu.so
aspose/pygc.cpython-313-x86_64-linux-gnu.so
aspose/pygc.cpython-38-x86_64-linux-gnu.so
aspose/pygc.cpython-39-x86_64-linux-gnu.so
aspose/pyreflection.cpython-310-x86_64-linux-gnu.so
aspose/pyreflection.cpython-311-x86_64-linux-gnu.so
aspose/pyreflection.cpython-312-x86_64-linux-gnu.so
aspose/pyreflection.cpython-313-x86_64-linux-gnu.so
aspose/pyreflection.cpython-38-x86_64-linux-gnu.so
aspose/pyreflection.cpython-39-x86_64-linux-gnu.so
aspose/__pyinstaller/__init__.pyi
aspose/__pyinstaller/hook-aspose.py
aspose/assemblies/cellsgridjs/Aspose.Cells.GridJs.dll
aspose_cells_gridjs_net_python-26.1.0.dist-info/METADATA
aspose_cells_gridjs_net_python-26.1.0.dist-info/WHEEL
aspose_cells_gridjs_net_python-26.1.0.dist-info/entry_points.txt
aspose_cells_gridjs_net_python-26.1.0.dist-info/top_level.txt
aspose_cells_gridjs_net_python-26.1.0.dist-info/RECORD