Metadata-Version: 2.1
Name: aspose-cells-gridjs-net-python
Version: 26.1.0
Summary: Aspose.Cells.GridJs for Python via .NET is a lightweight, scalable, and customizable toolkit that provides cross-platform web applications, enables convenient development for editing or viewing Excel/Spreadsheet files, offers simple deployment, and provides easy-to-use APIs.
Home-page: https://products.aspose.com/cells/
Author: aspose-cells
License: https://company.aspose.com/legal/eula
Project-URL: API Reference, https://reference.aspose.com/cells/python-net/
Project-URL: Docs, https://docs.aspose.com/cells/python-net/
Project-URL: Release Notes, https://releases.aspose.com/cells/python-net/release-notes/2025/aspose-cells-for-python-net-25-9-release-notes/
Project-URL: Blog, https://blog.aspose.com/category/cells/
Project-URL: Free support, https://forum.aspose.com/c/cells/
Project-URL: Temporary License, https://purchase.aspose.com/temporary-license/
Keywords: Excel,Editor,Data,Viewer,Chart,Formula,Pivot,Excel Editor,Excel Viewer,Excel_Editor,Excel_Viewer,Data Format,Data Convert,Spreadsheet Editor,Spreadsheet Viewer,Spreadsheet_Editor,Spreadsheet_Viewer,Online Office,Formula Calculation,view,edit,office,Excel,XLS,XLSX,XLSB,CSV,PDF,JPG,PNG,HTML,ODS,Numbers,XLSM,OOXML,Spreadsheet,Markdown,XPS,DOCX,PPTX,MHTML,TXT,JSON,SVG,EMF,TIFF,JSON,XML
Platform: linux_x86_64
Classifier: Intended Audience :: Developers
Classifier: Intended Audience :: Education
Classifier: Intended Audience :: Manufacturing
Classifier: Intended Audience :: Science/Research
Classifier: Operating System :: Microsoft :: Windows
Classifier: Operating System :: POSIX :: Linux
Classifier: Operating System :: Unix
Classifier: Operating System :: MacOS :: MacOS X
Classifier: License :: Free To Use But Restricted
Classifier: License :: Other/Proprietary License
Classifier: Programming Language :: Python :: 3.8
Classifier: Programming Language :: Python :: 3.9
Classifier: Programming Language :: Python :: 3.10
Classifier: Programming Language :: Python :: 3.11
Classifier: Programming Language :: Python :: 3.12
Classifier: Programming Language :: Python :: 3.13
Classifier: Topic :: Software Development :: Libraries
Requires-Python: >=3.8,<3.14
